jsonstate/__init__.py
jsonstate-0.0.6.dist-info/METADATA
jsonstate-0.0.6.dist-info/WHEEL
jsonstate-0.0.6.dist-info/RECORD
